{"savableCities":[{"name":"Area of Sizes and Scolds","type":"your home","population":11958,"posX":12,"posY":15,"posZ":99,"color":{"r":0.7431368827819824,"g":0.8296446204185486,"b":0.7862389087677002,"a":1.0},"leader":{"firstName":"Roma","lastName":"Brian","profession":"vagrant"},"armies":{"savableArmies":[{"leader":{"firstName":"Lorenzo","lastName":"Terry","profession":"general"},"soldiers":19,"posX":12,"posY":15,"isStored":true,"primaryObjective":0,"primaryObjectivePosX":0,"primaryObjectivePosY":0,"secondaryObjective":0,"secondaryObjectivePosX":0,"secondaryObjectivePosY":0},{"leader":{"firstName":"Mitsue","lastName":"Erich","profession":"general"},"soldiers":14,"posX":12,"posY":15,"isStored":true,"primaryObjective":0,"primaryObjectivePosX":0,"primaryObjectivePosY":0,"secondaryObjective":0,"secondaryObjectivePosX":0,"secondaryObjectivePosY":0}]}},{"name":"Fiestas","type":"city","population":16212,"posX":12,"posY":8,"posZ":99,"color":{"r":0.769102156162262,"g":0.7914646863937378,"b":0.7421322464942932,"a":1.0},"leader":{"firstName":"Samuel","lastName":"Cyrus","profession":"vagrant"},"armies":{"savableArmies":[{"leader":{"firstName":"Sherill","lastName":"Ernesto","profession":"general"},"soldiers":14,"posX":12,"posY":8,"isStored":true,"primaryObjective":0,"primaryObjectivePosX":0,"primaryObjectivePosY":0,"secondaryObjective":0,"secondaryObjectivePosX":0,"secondaryObjectivePosY":0},{"leader":{"firstName":"Dante","lastName":"Billie","profession":"general"},"soldiers":19,"posX":12,"posY":8,"isStored":true,"primaryObjective":0,"primaryObjectivePosX":0,"primaryObjectivePosY":0,"secondaryObjective":0,"secondaryObjectivePosX":0,"secondaryObjectivePosY":0}]}}]}